{"bill":{"bill_id":1551268,"change_hash":"b66804510f049de1731eb31a89e16614","session_id":1831,"session":{"session_id":1831,"state_id":44,"year_start":2022,"year_end":2022,"prefile":0,"sine_die":1,"prior":0,"special":0,"session_tag":"Regular Session","session_title":"2022 Regular Session","session_name":"2022 General Session"},"url":"https:\/\/legiscan.com\/UT\/bill\/HB0137\/2022","state_link":"https:\/\/le.utah.gov\/~2022\/bills\/static\/HB0137.html","completed":1,"status":4,"status_date":"2022-03-22","progress":[{"date":"2022-01-18","event":1},{"date":"2022-01-20","event":9},{"date":"2022-02-04","event":10},{"date":"2022-02-14","event":2},{"date":"2022-02-15","event":9},{"date":"2022-02-17","event":10},{"date":"2022-03-10","event":3},{"date":"2022-03-22","event":4}],"state":"UT","state_id":44,"bill_number":"HB0137","bill_type":"B","bill_type_id":"1","body":"H","body_id":93,"current_body":"H","current_body_id":93,"title":"DUI Amendments","description":"DUI Amendments","pending_committee_id":0,"committee":[],"referrals":[{"date":"2022-01-18","committee_id":2116,"chamber":"H","chamber_id":93,"name":"Rules"},{"date":"2022-01-20","committee_id":2110,"chamber":"H","chamber_id":93,"name":"Law Enforcement and Criminal Justice"},{"date":"2022-02-14","committee_id":2128,"chamber":"S","chamber_id":94,"name":"Rules"},{"date":"2022-02-15","committee_id":3583,"chamber":"S","chamber_id":94,"name":"Transportation, Public Utilities, Energy, and Technology"}],"history":[{"date":"2022-01-11","action":"Bill Numbered but not Distributed in Legislative Research and General Counsel","chamber":"","chamber_id":0,"importance":0},{"date":"2022-01-11","action":"Numbered Bill Publicly Distributed in Legislative Research and General Counsel","chamber":"","chamber_id":0,"importance":0},{"date":"2022-01-11","action":"LFA\/ bill sent to agencies for fiscal input in Legislative Research and General Counsel","chamber":"","chamber_id":0,"importance":0},{"date":"2022-01-12","action":"House\/ received bill from Legislative Research in Clerk of the House","chamber":"H","chamber_id":93,"importance":0},{"date":"2022-01-17","action":"LFA\/ fiscal note sent to sponsor in Clerk of the House","chamber":"H","chamber_id":93,"importance":0},{"date":"2022-01-18","action":"House\/ 1st reading (Introduced) in House Rules Committee","chamber":"H","chamber_id":93,"importance":1},{"date":"2022-01-18","action":"LFA\/ fiscal note publicly available in House Rules Committee","chamber":"H","chamber_id":93,"importance":0},{"date":"2022-01-19","action":"House\/ received fiscal note from Fiscal Analyst in House Rules Committee","chamber":"H","chamber_id":93,"importance":0},{"date":"2022-01-20","action":"House\/ to standing committee in House Law Enforcement and Criminal Justice Committee","chamber":"H","chamber_id":93,"importance":1},{"date":"2022-01-26","action":"House Comm - Not Considered in House Law Enforcement and Criminal Justice Committee","chamber":"H","chamber_id":93,"importance":0},{"date":"2022-02-03","action":"House Comm - Favorable Recommendation in House Law Enforcement and Criminal Justice Committee","chamber":"H","chamber_id":93,"importance":0},{"date":"2022-02-04","action":"House\/ committee report favorable in House Law Enforcement and Criminal Justice Committee","chamber":"H","chamber_id":93,"importance":1},{"date":"2022-02-04","action":"House\/ 2nd reading in House 3rd Reading Calendar for House bills","chamber":"H","chamber_id":93,"importance":0},{"date":"2022-02-11","action":"House\/ 3rd reading in House 3rd Reading Calendar for House bills","chamber":"H","chamber_id":93,"importance":0},{"date":"2022-02-11","action":"House\/ passed 3rd reading in Senate Secretary","chamber":"S","chamber_id":94,"importance":0},{"date":"2022-02-11","action":"House\/ to Senate in Senate Secretary","chamber":"S","chamber_id":94,"importance":0},{"date":"2022-02-14","action":"Senate\/ received from House in Waiting for Introduction in the Senate","chamber":"S","chamber_id":94,"importance":1},{"date":"2022-02-14","action":"Senate\/ 1st reading (Introduced) in Senate Rules Committee","chamber":"S","chamber_id":94,"importance":0},{"date":"2022-02-15","action":"Senate\/ to standing committee in Senate Transportation, Public Utilities, Energy, and Technology Committee","chamber":"S","chamber_id":94,"importance":1},{"date":"2022-02-17","action":"Senate Comm - Favorable Recommendation in Senate Transportation, Public Utilities, Energy, and Technology Committee","chamber":"S","chamber_id":94,"importance":0},{"date":"2022-02-17","action":"Senate Comm - Consent Calendar Recommendation in Senate Transportation, Public Utilities, Energy, and Technology Committee","chamber":"S","chamber_id":94,"importance":0},{"date":"2022-02-17","action":"Senate\/ comm rpt\/ placed on Consent Calendar in Senate Transportation, Public Utilities, Energy, and Technology Committee","chamber":"S","chamber_id":94,"importance":1},{"date":"2022-02-17","action":"Senate\/ 2nd reading in Senate Consent Calendar","chamber":"S","chamber_id":94,"importance":0},{"date":"2022-02-23","action":"Senate\/ 3rd reading in Senate Consent Calendar","chamber":"S","chamber_id":94,"importance":0},{"date":"2022-02-23","action":"Senate\/ passed 3rd reading in Senate President","chamber":"S","chamber_id":94,"importance":0},{"date":"2022-02-23","action":"Senate\/ signed by President\/ returned to House in House Speaker","chamber":"H","chamber_id":93,"importance":0},{"date":"2022-02-23","action":"Senate\/ to House in House Speaker","chamber":"H","chamber_id":93,"importance":0},{"date":"2022-02-23","action":"House\/ received from Senate in House Speaker","chamber":"H","chamber_id":93,"importance":0},{"date":"2022-02-23","action":"House\/ signed by Speaker\/ sent for enrolling in Legislative Research and General Counsel \/ Enrolling","chamber":"","chamber_id":0,"importance":0},{"date":"2022-02-25","action":"Bill Received from House for Enrolling in Legislative Research and General Counsel \/ Enrolling","chamber":"","chamber_id":0,"importance":0},{"date":"2022-02-25","action":"Draft of Enrolled Bill Prepared in Legislative Research and General Counsel \/ Enrolling","chamber":"","chamber_id":0,"importance":0},{"date":"2022-03-10","action":"Enrolled Bill Returned to House or Senate in Clerk of the House","chamber":"H","chamber_id":93,"importance":0},{"date":"2022-03-10","action":"House\/ enrolled bill to Printing in Clerk of the House","chamber":"H","chamber_id":93,"importance":1},{"date":"2022-03-10","action":"House\/ to Governor in Executive Branch - Governor","chamber":"","chamber_id":0,"importance":0},{"date":"2022-03-22","action":"Governor Signed in Lieutenant Governor's office for filing","chamber":"","chamber_id":0,"importance":1}],"sponsors":[{"people_id":12088,"person_hash":"jyird9oq","party_id":"2","state_id":44,"party":"R","role_id":1,"role":"Rep","name":"Steve Eliason","first_name":"Steve","middle_name":"","last_name":"Eliason","suffix":"","nickname":"","district":"HD-045","ftm_eid":6684185,"votesmart_id":121355,"opensecrets_id":"","knowwho_pid":293061,"ballotpedia":"Steven_Eliason","sponsor_type_id":1,"sponsor_order":1,"committee_sponsor":0,"committee_id":0,"state_federal":0},{"people_id":8111,"person_hash":"8d1fqrw0","party_id":"2","state_id":44,"party":"R","role_id":2,"role":"Sen","name":"Curtis Bramble","first_name":"Curtis","middle_name":"S.","last_name":"Bramble","suffix":"","nickname":"Curt","district":"SD-016","ftm_eid":6647149,"votesmart_id":50308,"opensecrets_id":"","knowwho_pid":208594,"ballotpedia":"Curtis_Bramble","sponsor_type_id":3,"sponsor_order":2,"committee_sponsor":0,"committee_id":0,"state_federal":0}],"sasts":[],"subjects":[{"subject_id":11866,"subject_name":"Law Enforcement and Criminal Justice"},{"subject_id":11903,"subject_name":"Driving Under the Influence (DUI)"},{"subject_id":332736,"subject_name":"Crimes"},{"subject_id":11875,"subject_name":"Transportation"}],"texts":[{"doc_id":2470697,"date":"2022-01-11","type":"Introduced","type_id":1,"mime":"application\/pdf","mime_id":2,"url":"https:\/\/legiscan.com\/UT\/text\/HB0137\/id\/2470697","state_link":"https:\/\/le.utah.gov\/~2022\/bills\/hbillint\/HB0137.pdf","text_size":156349,"text_hash":"c8b65856ecf29d4602b055a4c290c85f"},{"doc_id":2544630,"date":"2022-03-10","type":"Enrolled","type_id":5,"mime":"application\/pdf","mime_id":2,"url":"https:\/\/legiscan.com\/UT\/text\/HB0137\/id\/2544630","state_link":"https:\/\/le.utah.gov\/~2022\/bills\/hbillenr\/HB0137.pdf","text_size":145674,"text_hash":"38c64f8068fc7b554994f4aa13e8c37a"}],"votes":[{"roll_call_id":1134478,"date":"2022-02-03","desc":"House Comm - Favorable Recommendation","yea":8,"nay":0,"nv":0,"absent":3,"total":11,"passed":1,"chamber":"H","chamber_id":93,"url":"https:\/\/legiscan.com\/UT\/rollcall\/HB0137\/id\/1134478","state_link":"https:\/\/le.utah.gov\/mtgvotes.jsp?voteid=22577"},{"roll_call_id":1141436,"date":"2022-02-11","desc":"House\/ passed 3rd reading","yea":68,"nay":2,"nv":0,"absent":5,"total":75,"passed":1,"chamber":"H","chamber_id":93,"url":"https:\/\/legiscan.com\/UT\/rollcall\/HB0137\/id\/1141436","state_link":"https:\/\/le.utah.gov\/DynaBill\/svotes.jsp?sessionid=2022GS&voteid=365&house=H"},{"roll_call_id":1147071,"date":"2022-02-17","desc":"Senate Comm - Favorable Recommendation","yea":4,"nay":0,"nv":0,"absent":4,"total":8,"passed":1,"chamber":"S","chamber_id":94,"url":"https:\/\/legiscan.com\/UT\/rollcall\/HB0137\/id\/1147071","state_link":"https:\/\/le.utah.gov\/mtgvotes.jsp?voteid=23505"},{"roll_call_id":1147072,"date":"2022-02-17","desc":"Senate Comm - Consent Calendar Recommendation","yea":4,"nay":0,"nv":0,"absent":4,"total":8,"passed":1,"chamber":"S","chamber_id":94,"url":"https:\/\/legiscan.com\/UT\/rollcall\/HB0137\/id\/1147072","state_link":"https:\/\/le.utah.gov\/mtgvotes.jsp?voteid=23506"},{"roll_call_id":1151303,"date":"2022-02-23","desc":"Senate\/ passed 3rd reading","yea":22,"nay":0,"nv":0,"absent":7,"total":29,"passed":1,"chamber":"S","chamber_id":94,"url":"https:\/\/legiscan.com\/UT\/rollcall\/HB0137\/id\/1151303","state_link":"https:\/\/le.utah.gov\/DynaBill\/svotes.jsp?sessionid=2022GS&voteid=992&house=S"}],"amendments":[],"supplements":[{"supplement_id":222018,"date":"2022-01-12","type":"Misc","type_id":7,"title":"Misc","description":"Agency Perf Note HB0137","mime":"application\/pdf","mime_id":2,"url":"https:\/\/legiscan.com\/UT\/supplement\/HB0137\/id\/222018","state_link":"https:\/\/le.utah.gov\/lfa\/fnotes\/2022\/HB0137.pna.pdf","supplement_size":1388478,"supplement_hash":"6529c6179de6af0d2d1fd863feb32637"},{"supplement_id":224212,"date":"2022-01-18","type":"Fiscal Note","type_id":1,"title":"Fiscal Note","description":"Fiscal Note HB0137","mime":"application\/pdf","mime_id":2,"url":"https:\/\/legiscan.com\/UT\/supplement\/HB0137\/id\/224212","state_link":"https:\/\/le.utah.gov\/lfa\/fnotes\/2022\/HB0137.fn.pdf","supplement_size":1391805,"supplement_hash":"aaf04bcc186c1b06c0754590a3dbd71d"}],"calendar":[{"type_id":1,"type":"Hearing","date":"2022-01-26","time":"14:00","location":"","description":"House Law Enforcement and Criminal Justice Hearing"},{"type_id":1,"type":"Hearing","date":"2022-02-03","time":"16:00","location":"","description":"House Law Enforcement and Criminal Justice Hearing"},{"type_id":1,"type":"Hearing","date":"2022-02-17","time":"08:35","location":"","description":"Senate Transportation, Public Utilities, Energy, and Technology Hearing"}]}}