{"bill":{"bill_id":1573901,"change_hash":"2108eb7aca1b831c8f2395e695bbc482","session_id":1831,"session":{"session_id":1831,"state_id":44,"year_start":2022,"year_end":2022,"prefile":0,"sine_die":1,"prior":0,"special":0,"session_tag":"Regular Session","session_title":"2022 Regular Session","session_name":"2022 General Session"},"url":"https:\/\/legiscan.com\/UT\/bill\/HB0236\/2022","state_link":"https:\/\/le.utah.gov\/~2022\/bills\/static\/HB0236.html","completed":1,"status":4,"status_date":"2022-03-22","progress":[{"date":"2022-01-27","event":1},{"date":"2022-02-04","event":9},{"date":"2022-02-08","event":10},{"date":"2022-02-14","event":2},{"date":"2022-02-16","event":9},{"date":"2022-02-22","event":10},{"date":"2022-03-10","event":3},{"date":"2022-03-22","event":4}],"state":"UT","state_id":44,"bill_number":"HB0236","bill_type":"B","bill_type_id":"1","body":"H","body_id":93,"current_body":"H","current_body_id":93,"title":"Behavioral Health Amendments","description":"Behavioral Health Amendments","pending_committee_id":0,"committee":[],"referrals":[{"date":"2022-01-27","committee_id":2116,"chamber":"H","chamber_id":93,"name":"Rules"},{"date":"2022-02-04","committee_id":2108,"chamber":"H","chamber_id":93,"name":"Health and Human Services"},{"date":"2022-02-14","committee_id":2128,"chamber":"S","chamber_id":94,"name":"Rules"},{"date":"2022-02-16","committee_id":2123,"chamber":"S","chamber_id":94,"name":"Health and Human Services"}],"history":[{"date":"2022-01-26","action":"Bill Numbered but not Distributed in Legislative Research and General Counsel","chamber":"","chamber_id":0,"importance":0},{"date":"2022-01-26","action":"Numbered Bill Publicly Distributed in Legislative Research and General Counsel","chamber":"","chamber_id":0,"importance":0},{"date":"2022-01-26","action":"LFA\/ bill sent to agencies for fiscal input in Legislative Research and General Counsel","chamber":"","chamber_id":0,"importance":0},{"date":"2022-01-27","action":"House\/ received bill from Legislative Research in Clerk of the House","chamber":"H","chamber_id":93,"importance":0},{"date":"2022-01-27","action":"House\/ 1st reading (Introduced) in House Rules Committee","chamber":"H","chamber_id":93,"importance":1},{"date":"2022-01-31","action":"LFA\/ fiscal note sent to sponsor in House Rules Committee","chamber":"H","chamber_id":93,"importance":0},{"date":"2022-01-31","action":"LFA\/ fiscal note publicly available in House Rules Committee","chamber":"H","chamber_id":93,"importance":0},{"date":"2022-01-31","action":"House\/ received fiscal note from Fiscal Analyst in House Rules Committee","chamber":"H","chamber_id":93,"importance":0},{"date":"2022-02-04","action":"House\/ to standing committee in House Health and Human Services Committee","chamber":"H","chamber_id":93,"importance":1},{"date":"2022-02-07","action":"House Comm - Favorable Recommendation in House Health and Human Services Committee","chamber":"H","chamber_id":93,"importance":0},{"date":"2022-02-08","action":"House\/ committee report favorable in House Health and Human Services Committee","chamber":"H","chamber_id":93,"importance":1},{"date":"2022-02-08","action":"House\/ 2nd reading in House 3rd Reading Calendar for House bills","chamber":"H","chamber_id":93,"importance":0},{"date":"2022-02-14","action":"House\/ 3rd reading in House 3rd Reading Calendar for House bills","chamber":"H","chamber_id":93,"importance":0},{"date":"2022-02-14","action":"House\/ passed 3rd reading in Senate Secretary","chamber":"S","chamber_id":94,"importance":0},{"date":"2022-02-14","action":"House\/ to Senate in Senate Secretary","chamber":"S","chamber_id":94,"importance":0},{"date":"2022-02-14","action":"Senate\/ received from House in Waiting for Introduction in the Senate","chamber":"S","chamber_id":94,"importance":1},{"date":"2022-02-14","action":"Senate\/ 1st reading (Introduced) in Senate Rules Committee","chamber":"S","chamber_id":94,"importance":0},{"date":"2022-02-16","action":"Senate\/ to standing committee in Senate Health and Human Services Committee","chamber":"S","chamber_id":94,"importance":1},{"date":"2022-02-22","action":"Senate Comm - Favorable Recommendation in Senate Health and Human Services Committee","chamber":"S","chamber_id":94,"importance":0},{"date":"2022-02-22","action":"Senate\/ committee report favorable in Senate Health and Human Services Committee","chamber":"S","chamber_id":94,"importance":1},{"date":"2022-02-22","action":"Senate\/ placed on 2nd Reading Calendar in Senate 2nd Reading Calendar","chamber":"S","chamber_id":94,"importance":0},{"date":"2022-02-24","action":"Senate\/ 2nd reading in Senate 2nd Reading Calendar","chamber":"S","chamber_id":94,"importance":0},{"date":"2022-02-24","action":"Senate\/ passed 2nd reading in Senate 3rd Reading Calendar","chamber":"S","chamber_id":94,"importance":0},{"date":"2022-02-24","action":"Senate\/ placed on 3rd Reading Calendar table in Senate 3rd Reading Calendar Table","chamber":"S","chamber_id":94,"importance":0},{"date":"2022-03-01","action":"Senate\/ placed back on 3rd Reading Calendar in Senate Substituted Bill","chamber":"S","chamber_id":94,"importance":0},{"date":"2022-03-01","action":"Senate\/ 3rd reading in Senate 3rd Reading Calendar","chamber":"S","chamber_id":94,"importance":0},{"date":"2022-03-01","action":"Senate\/ passed 3rd reading in Senate President","chamber":"S","chamber_id":94,"importance":0},{"date":"2022-03-01","action":"Senate\/ signed by President\/ returned to House in House Speaker","chamber":"H","chamber_id":93,"importance":0},{"date":"2022-03-01","action":"Senate\/ to House in House Speaker","chamber":"H","chamber_id":93,"importance":0},{"date":"2022-03-01","action":"House\/ received from Senate in House Speaker","chamber":"H","chamber_id":93,"importance":0},{"date":"2022-03-01","action":"House\/ signed by Speaker\/ sent for enrolling in Legislative Research and General Counsel \/ Enrolling","chamber":"","chamber_id":0,"importance":0},{"date":"2022-03-03","action":"Bill Received from House for Enrolling in Legislative Research and General Counsel \/ Enrolling","chamber":"","chamber_id":0,"importance":0},{"date":"2022-03-03","action":"Draft of Enrolled Bill Prepared in Legislative Research and General Counsel \/ Enrolling","chamber":"","chamber_id":0,"importance":0},{"date":"2022-03-10","action":"Enrolled Bill Returned to House or Senate in Clerk of the House","chamber":"H","chamber_id":93,"importance":0},{"date":"2022-03-10","action":"House\/ enrolled bill to Printing in Clerk of the House","chamber":"H","chamber_id":93,"importance":1},{"date":"2022-03-10","action":"House\/ to Governor in Executive Branch - Governor","chamber":"","chamber_id":0,"importance":0},{"date":"2022-03-22","action":"Governor Signed in Lieutenant Governor's office for filing","chamber":"","chamber_id":0,"importance":1}],"sponsors":[{"people_id":12088,"person_hash":"jyird9oq","party_id":"2","state_id":44,"party":"R","role_id":1,"role":"Rep","name":"Steve Eliason","first_name":"Steve","middle_name":"","last_name":"Eliason","suffix":"","nickname":"","district":"HD-045","ftm_eid":6684185,"votesmart_id":121355,"opensecrets_id":"","knowwho_pid":293061,"ballotpedia":"Steven_Eliason","sponsor_type_id":1,"sponsor_order":1,"committee_sponsor":0,"committee_id":0,"state_federal":0},{"people_id":13816,"person_hash":"mw9323ln","party_id":"2","state_id":44,"party":"R","role_id":2,"role":"Sen","name":"Todd Weiler","first_name":"Todd","middle_name":"D.","last_name":"Weiler","suffix":"","nickname":"","district":"SD-023","ftm_eid":6648183,"votesmart_id":50569,"opensecrets_id":"","knowwho_pid":390467,"ballotpedia":"Todd_Weiler","sponsor_type_id":3,"sponsor_order":2,"committee_sponsor":0,"committee_id":0,"state_federal":0}],"sasts":[],"subjects":[{"subject_id":11942,"subject_name":"Human Services"},{"subject_id":334430,"subject_name":"Health Insurance"},{"subject_id":12031,"subject_name":"Substance Abuse"},{"subject_id":11862,"subject_name":"Health"},{"subject_id":11893,"subject_name":"Health Care"},{"subject_id":12052,"subject_name":"Health Care Facilities"},{"subject_id":83179,"subject_name":"Mental Health Facilities"},{"subject_id":12007,"subject_name":"Mental Health"},{"subject_id":332644,"subject_name":"Health Care Professionals"},{"subject_id":332727,"subject_name":"Mental Health Professionals"},{"subject_id":255958,"subject_name":"Suicide"},{"subject_id":11951,"subject_name":"Department of Human Services"},{"subject_id":11952,"subject_name":"Medicaid"},{"subject_id":342080,"subject_name":"Crisis Line"},{"subject_id":340446,"subject_name":"Local Mental Health Authorities"},{"subject_id":342611,"subject_name":"Local Substance Abuse Authorities"},{"subject_id":334875,"subject_name":"Substance Abuse and Mental Health"},{"subject_id":334876,"subject_name":"Substance Use Disorder Treatment"}],"texts":[{"doc_id":2492891,"date":"2022-01-26","type":"Introduced","type_id":1,"mime":"application\/pdf","mime_id":2,"url":"https:\/\/legiscan.com\/UT\/text\/HB0236\/id\/2492891","state_link":"https:\/\/le.utah.gov\/~2022\/bills\/hbillint\/HB0236.pdf","text_size":118296,"text_hash":"3916c968fcfee54a41be4e28c1262e77"},{"doc_id":2545087,"date":"2022-03-10","type":"Enrolled","type_id":5,"mime":"application\/pdf","mime_id":2,"url":"https:\/\/legiscan.com\/UT\/text\/HB0236\/id\/2545087","state_link":"https:\/\/le.utah.gov\/~2022\/bills\/hbillenr\/HB0236.pdf","text_size":106936,"text_hash":"5d0e4d94f9ae1c34c1165c16342081d1"}],"votes":[{"roll_call_id":1136922,"date":"2022-02-07","desc":"House Comm - Favorable Recommendation","yea":11,"nay":0,"nv":0,"absent":2,"total":13,"passed":1,"chamber":"H","chamber_id":93,"url":"https:\/\/legiscan.com\/UT\/rollcall\/HB0236\/id\/1136922","state_link":"https:\/\/le.utah.gov\/mtgvotes.jsp?voteid=22787"},{"roll_call_id":1142801,"date":"2022-02-14","desc":"House\/ passed 3rd reading","yea":69,"nay":0,"nv":0,"absent":6,"total":75,"passed":1,"chamber":"H","chamber_id":93,"url":"https:\/\/legiscan.com\/UT\/rollcall\/HB0236\/id\/1142801","state_link":"https:\/\/le.utah.gov\/DynaBill\/svotes.jsp?sessionid=2022GS&voteid=426&house=H"},{"roll_call_id":1150426,"date":"2022-02-22","desc":"Senate Comm - Favorable Recommendation","yea":6,"nay":0,"nv":0,"absent":2,"total":8,"passed":1,"chamber":"S","chamber_id":94,"url":"https:\/\/legiscan.com\/UT\/rollcall\/HB0236\/id\/1150426","state_link":"https:\/\/le.utah.gov\/mtgvotes.jsp?voteid=23669"},{"roll_call_id":1154757,"date":"2022-02-24","desc":"Senate\/ passed 2nd reading","yea":25,"nay":0,"nv":0,"absent":4,"total":29,"passed":1,"chamber":"S","chamber_id":94,"url":"https:\/\/legiscan.com\/UT\/rollcall\/HB0236\/id\/1154757","state_link":"https:\/\/le.utah.gov\/DynaBill\/svotes.jsp?sessionid=2022GS&voteid=1159&house=S"},{"roll_call_id":1158531,"date":"2022-03-01","desc":"Senate\/ passed 3rd reading","yea":27,"nay":0,"nv":0,"absent":2,"total":29,"passed":1,"chamber":"S","chamber_id":94,"url":"https:\/\/legiscan.com\/UT\/rollcall\/HB0236\/id\/1158531","state_link":"https:\/\/le.utah.gov\/DynaBill\/svotes.jsp?sessionid=2022GS&voteid=1443&house=S"}],"amendments":[],"supplements":[{"supplement_id":231171,"date":"2022-01-31","type":"Fiscal Note","type_id":1,"title":"Fiscal Note","description":"Fiscal Note HB0236","mime":"application\/pdf","mime_id":2,"url":"https:\/\/legiscan.com\/UT\/supplement\/HB0236\/id\/231171","state_link":"https:\/\/le.utah.gov\/lfa\/fnotes\/2022\/HB0236.fn.pdf","supplement_size":1392979,"supplement_hash":"898ea7b0bd0e3657acd14521a2e4fba1"}],"calendar":[{"type_id":1,"type":"Hearing","date":"2022-02-07","time":"15:40","location":"","description":"House Health and Human Services Hearing"},{"type_id":1,"type":"Hearing","date":"2022-02-22","time":"08:00","location":"","description":"Senate Health and Human Services Hearing"}]}}