{"bill":{"bill_id":1590185,"change_hash":"071af04d5c6dd51a34abe590533d5221","session_id":1831,"session":{"session_id":1831,"state_id":44,"year_start":2022,"year_end":2022,"prefile":0,"sine_die":1,"prior":0,"special":0,"session_tag":"Regular Session","session_title":"2022 Regular Session","session_name":"2022 General Session"},"url":"https:\/\/legiscan.com\/UT\/bill\/HB0391\/2022","state_link":"https:\/\/le.utah.gov\/~2022\/bills\/static\/HB0391.html","completed":1,"status":4,"status_date":"2022-03-22","progress":[{"date":"2022-02-15","event":1},{"date":"2022-02-17","event":9},{"date":"2022-02-23","event":10},{"date":"2022-02-25","event":2},{"date":"2022-02-25","event":9},{"date":"2022-03-01","event":10},{"date":"2022-03-11","event":3},{"date":"2022-03-22","event":4}],"state":"UT","state_id":44,"bill_number":"HB0391","bill_type":"B","bill_type_id":"1","body":"H","body_id":93,"current_body":"H","current_body_id":93,"title":"Autocycle Amendments","description":"Autocycle Amendments","pending_committee_id":0,"committee":[],"referrals":[{"date":"2022-02-15","committee_id":2116,"chamber":"H","chamber_id":93,"name":"Rules"},{"date":"2022-02-17","committee_id":2117,"chamber":"H","chamber_id":93,"name":"Transportation"},{"date":"2022-02-25","committee_id":2128,"chamber":"S","chamber_id":94,"name":"Rules"},{"date":"2022-02-25","committee_id":3583,"chamber":"S","chamber_id":94,"name":"Transportation, Public Utilities, Energy, and Technology"}],"history":[{"date":"2022-02-14","action":"Bill Numbered but not Distributed in Legislative Research and General Counsel","chamber":"","chamber_id":0,"importance":0},{"date":"2022-02-14","action":"Numbered Bill Publicly Distributed in Legislative Research and General Counsel","chamber":"","chamber_id":0,"importance":0},{"date":"2022-02-14","action":"LFA\/ bill sent to agencies for fiscal input in Legislative Research and General Counsel","chamber":"","chamber_id":0,"importance":0},{"date":"2022-02-15","action":"House\/ received bill from Legislative Research in Clerk of the House","chamber":"H","chamber_id":93,"importance":0},{"date":"2022-02-15","action":"House\/ 1st reading (Introduced) in House Rules Committee","chamber":"H","chamber_id":93,"importance":1},{"date":"2022-02-16","action":"LFA\/ fiscal note publicly available in House Rules Committee","chamber":"H","chamber_id":93,"importance":0},{"date":"2022-02-16","action":"House\/ received fiscal note from Fiscal Analyst in House Rules Committee","chamber":"H","chamber_id":93,"importance":0},{"date":"2022-02-17","action":"House\/ to standing committee in House Transportation Committee","chamber":"H","chamber_id":93,"importance":1},{"date":"2022-02-23","action":"House Comm - Favorable Recommendation in House Transportation Committee","chamber":"H","chamber_id":93,"importance":0},{"date":"2022-02-23","action":"House Comm - Consent Calendar Recommendation in House Transportation Committee","chamber":"H","chamber_id":93,"importance":0},{"date":"2022-02-23","action":"House\/ comm rpt\/ placed on Consent Calendar in House Transportation Committee","chamber":"H","chamber_id":93,"importance":1},{"date":"2022-02-23","action":"House\/ 2nd reading in House Consent Calendar","chamber":"H","chamber_id":93,"importance":0},{"date":"2022-02-25","action":"House\/ 3rd reading in House Consent Calendar","chamber":"H","chamber_id":93,"importance":0},{"date":"2022-02-25","action":"House\/ passed 3rd reading in Senate Secretary","chamber":"S","chamber_id":94,"importance":0},{"date":"2022-02-25","action":"House\/ to Senate in Senate Secretary","chamber":"S","chamber_id":94,"importance":0},{"date":"2022-02-25","action":"Senate\/ received from House in Waiting for Introduction in the Senate","chamber":"S","chamber_id":94,"importance":1},{"date":"2022-02-25","action":"Senate\/ 1st reading (Introduced) in Senate Rules Committee","chamber":"S","chamber_id":94,"importance":0},{"date":"2022-02-25","action":"Senate\/ to standing committee in Senate Transportation, Public Utilities, Energy, and Technology Committee","chamber":"S","chamber_id":94,"importance":1},{"date":"2022-03-01","action":"Senate Comm - Favorable Recommendation in Senate Transportation, Public Utilities, Energy, and Technology Committee","chamber":"S","chamber_id":94,"importance":0},{"date":"2022-03-01","action":"Senate Comm - Consent Calendar Recommendation in Senate Transportation, Public Utilities, Energy, and Technology Committee","chamber":"S","chamber_id":94,"importance":0},{"date":"2022-03-01","action":"Senate\/ comm rpt\/ placed on Consent Calendar in Senate Transportation, Public Utilities, Energy, and Technology Committee","chamber":"S","chamber_id":94,"importance":1},{"date":"2022-03-01","action":"Senate\/ 2nd reading in Senate Consent Calendar","chamber":"S","chamber_id":94,"importance":0},{"date":"2022-03-04","action":"Senate\/ 3rd reading in Senate Consent Calendar","chamber":"S","chamber_id":94,"importance":0},{"date":"2022-03-04","action":"Senate\/ passed 3rd reading in Senate President","chamber":"S","chamber_id":94,"importance":0},{"date":"2022-03-04","action":"Senate\/ signed by President\/ returned to House in House Speaker","chamber":"H","chamber_id":93,"importance":0},{"date":"2022-03-04","action":"Senate\/ to House in House Speaker","chamber":"H","chamber_id":93,"importance":0},{"date":"2022-03-04","action":"House\/ received from Senate in House Speaker","chamber":"H","chamber_id":93,"importance":0},{"date":"2022-03-04","action":"House\/ signed by Speaker\/ sent for enrolling in Legislative Research and General Counsel \/ Enrolling","chamber":"","chamber_id":0,"importance":0},{"date":"2022-03-08","action":"Bill Received from House for Enrolling in Legislative Research and General Counsel \/ Enrolling","chamber":"","chamber_id":0,"importance":0},{"date":"2022-03-08","action":"Draft of Enrolled Bill Prepared in Legislative Research and General Counsel \/ Enrolling","chamber":"","chamber_id":0,"importance":0},{"date":"2022-03-11","action":"Enrolled Bill Returned to House or Senate in Clerk of the House","chamber":"H","chamber_id":93,"importance":0},{"date":"2022-03-11","action":"House\/ enrolled bill to Printing in Clerk of the House","chamber":"H","chamber_id":93,"importance":1},{"date":"2022-03-14","action":"House\/ to Governor in Executive Branch - Governor","chamber":"","chamber_id":0,"importance":0},{"date":"2022-03-22","action":"Governor Signed in Lieutenant Governor's office for filing","chamber":"","chamber_id":0,"importance":1}],"sponsors":[{"people_id":15452,"person_hash":"vrlu99sr","party_id":"2","state_id":44,"party":"R","role_id":1,"role":"Rep","name":"Kay Christofferson","first_name":"Kay","middle_name":"J.","last_name":"Christofferson","suffix":"","nickname":"","district":"HD-056","ftm_eid":13007246,"votesmart_id":137523,"opensecrets_id":"","knowwho_pid":404922,"ballotpedia":"Kay_Christofferson","sponsor_type_id":1,"sponsor_order":1,"committee_sponsor":0,"committee_id":0,"state_federal":0},{"people_id":8150,"person_hash":"4bd3kg7n","party_id":"2","state_id":44,"party":"R","role_id":2,"role":"Sen","name":"Wayne Harper","first_name":"Wayne","middle_name":"A.","last_name":"Harper","suffix":"","nickname":"","district":"SD-006","ftm_eid":6606689,"votesmart_id":10551,"opensecrets_id":"","knowwho_pid":199346,"ballotpedia":"Wayne_Harper","sponsor_type_id":3,"sponsor_order":2,"committee_sponsor":0,"committee_id":0,"state_federal":0}],"sasts":[],"subjects":[{"subject_id":11957,"subject_name":"Motorcycles"},{"subject_id":11875,"subject_name":"Transportation"}],"texts":[{"doc_id":2515785,"date":"2022-02-14","type":"Introduced","type_id":1,"mime":"application\/pdf","mime_id":2,"url":"https:\/\/legiscan.com\/UT\/text\/HB0391\/id\/2515785","state_link":"https:\/\/le.utah.gov\/~2022\/bills\/hbillint\/HB0391.pdf","text_size":99360,"text_hash":"b0c0e60917eff6ec2ed226e865e8018f"},{"doc_id":2547231,"date":"2022-03-11","type":"Enrolled","type_id":5,"mime":"application\/pdf","mime_id":2,"url":"https:\/\/legiscan.com\/UT\/text\/HB0391\/id\/2547231","state_link":"https:\/\/le.utah.gov\/~2022\/bills\/hbillenr\/HB0391.pdf","text_size":87779,"text_hash":"98a16a5c4b6fbf370e703c23d0f0cb47"}],"votes":[{"roll_call_id":1151850,"date":"2022-02-23","desc":"House Comm - Favorable Recommendation","yea":8,"nay":0,"nv":0,"absent":4,"total":12,"passed":1,"chamber":"H","chamber_id":93,"url":"https:\/\/legiscan.com\/UT\/rollcall\/HB0391\/id\/1151850","state_link":"https:\/\/le.utah.gov\/mtgvotes.jsp?voteid=23806"},{"roll_call_id":1151851,"date":"2022-02-23","desc":"House Comm - Consent Calendar Recommendation","yea":8,"nay":0,"nv":0,"absent":4,"total":12,"passed":1,"chamber":"H","chamber_id":93,"url":"https:\/\/legiscan.com\/UT\/rollcall\/HB0391\/id\/1151851","state_link":"https:\/\/le.utah.gov\/mtgvotes.jsp?voteid=23807"},{"roll_call_id":1155408,"date":"2022-02-25","desc":"House\/ passed 3rd reading","yea":68,"nay":0,"nv":0,"absent":7,"total":75,"passed":1,"chamber":"H","chamber_id":93,"url":"https:\/\/legiscan.com\/UT\/rollcall\/HB0391\/id\/1155408","state_link":"https:\/\/le.utah.gov\/DynaBill\/svotes.jsp?sessionid=2022GS&voteid=818&house=H"},{"roll_call_id":1158102,"date":"2022-03-01","desc":"Senate Comm - Favorable Recommendation","yea":4,"nay":0,"nv":0,"absent":4,"total":8,"passed":1,"chamber":"S","chamber_id":94,"url":"https:\/\/legiscan.com\/UT\/rollcall\/HB0391\/id\/1158102","state_link":"https:\/\/le.utah.gov\/mtgvotes.jsp?voteid=24369"},{"roll_call_id":1158103,"date":"2022-03-01","desc":"Senate Comm - Consent Calendar Recommendation","yea":4,"nay":0,"nv":0,"absent":4,"total":8,"passed":1,"chamber":"S","chamber_id":94,"url":"https:\/\/legiscan.com\/UT\/rollcall\/HB0391\/id\/1158103","state_link":"https:\/\/le.utah.gov\/mtgvotes.jsp?voteid=24370"},{"roll_call_id":1163301,"date":"2022-03-04","desc":"Senate\/ passed 3rd reading","yea":27,"nay":0,"nv":0,"absent":2,"total":29,"passed":1,"chamber":"S","chamber_id":94,"url":"https:\/\/legiscan.com\/UT\/rollcall\/HB0391\/id\/1163301","state_link":"https:\/\/le.utah.gov\/DynaBill\/svotes.jsp?sessionid=2022GS&voteid=1683&house=S"}],"amendments":[],"supplements":[{"supplement_id":242225,"date":"2022-02-16","type":"Fiscal Note","type_id":1,"title":"Fiscal Note","description":"Fiscal Note HB0391","mime":"application\/pdf","mime_id":2,"url":"https:\/\/legiscan.com\/UT\/supplement\/HB0391\/id\/242225","state_link":"https:\/\/le.utah.gov\/lfa\/fnotes\/2022\/HB0391.fn.pdf","supplement_size":1390792,"supplement_hash":"8a9407de48fa1ae20d2dfb813e852080"}],"calendar":[{"type_id":1,"type":"Hearing","date":"2022-02-23","time":"08:00","location":"","description":"House Transportation Hearing"},{"type_id":1,"type":"Hearing","date":"2022-03-01","time":"09:15","location":"","description":"Senate Transportation, Public Utilities, Energy, and Technology Hearing"}]}}