{"bill":{"bill_id":1559735,"change_hash":"1dd84724a51c9aaade08b715fda6c0de","session_id":1831,"session":{"session_id":1831,"state_id":44,"year_start":2022,"year_end":2022,"prefile":0,"sine_die":1,"prior":0,"special":0,"session_tag":"Regular Session","session_title":"2022 Regular Session","session_name":"2022 General Session"},"url":"https:\/\/legiscan.com\/UT\/bill\/SB0098\/2022","state_link":"https:\/\/le.utah.gov\/~2022\/bills\/static\/SB0098.html","completed":1,"status":4,"status_date":"2022-03-23","progress":[{"date":"2022-01-18","event":1},{"date":"2022-01-21","event":9},{"date":"2022-01-27","event":10},{"date":"2022-02-04","event":2},{"date":"2022-02-07","event":9},{"date":"2022-02-16","event":10},{"date":"2022-03-11","event":3},{"date":"2022-03-23","event":4}],"state":"UT","state_id":44,"bill_number":"SB0098","bill_type":"B","bill_type_id":"1","body":"S","body_id":94,"current_body":"S","current_body_id":94,"title":"Judiciary Amendments","description":"Judiciary Amendments","pending_committee_id":0,"committee":[],"referrals":[{"date":"2022-01-18","committee_id":2128,"chamber":"S","chamber_id":94,"name":"Rules"},{"date":"2022-01-21","committee_id":2124,"chamber":"S","chamber_id":94,"name":"Judiciary, Law Enforcement, and Criminal Justice"},{"date":"2022-02-04","committee_id":2116,"chamber":"H","chamber_id":93,"name":"Rules"},{"date":"2022-02-07","committee_id":2109,"chamber":"H","chamber_id":93,"name":"Judiciary"}],"history":[{"date":"2022-01-14","action":"Bill Numbered but not Distributed in Legislative Research and General Counsel","chamber":"","chamber_id":0,"importance":0},{"date":"2022-01-14","action":"Numbered Bill Publicly Distributed in Legislative Research and General Counsel","chamber":"","chamber_id":0,"importance":0},{"date":"2022-01-18","action":"Senate\/ received bill from Legislative Research in Waiting for Introduction in the Senate","chamber":"S","chamber_id":94,"importance":0},{"date":"2022-01-18","action":"Senate\/ 1st reading (Introduced) in Senate Rules Committee","chamber":"S","chamber_id":94,"importance":1},{"date":"2022-01-19","action":"Senate\/ received fiscal note from Fiscal Analyst in Senate Rules Committee","chamber":"S","chamber_id":94,"importance":0},{"date":"2022-01-21","action":"Senate\/ to standing committee in Senate Judiciary, Law Enforcement, and Criminal Justice Committee","chamber":"S","chamber_id":94,"importance":1},{"date":"2022-01-25","action":"Senate Comm - Substitute Recommendation from # 0 to # 1 in Senate Judiciary, Law Enforcement, and Criminal Justice Committee","chamber":"S","chamber_id":94,"importance":0},{"date":"2022-01-25","action":"Senate Comm - Favorable Recommendation in Senate Judiciary, Law Enforcement, and Criminal Justice Committee","chamber":"S","chamber_id":94,"importance":0},{"date":"2022-01-27","action":"Senate\/ comm rpt\/ substituted in Senate Judiciary, Law Enforcement, and Criminal Justice Committee","chamber":"S","chamber_id":94,"importance":1},{"date":"2022-01-27","action":"Senate\/ placed on 2nd Reading Calendar in Senate 2nd Reading Calendar","chamber":"S","chamber_id":94,"importance":0},{"date":"2022-01-31","action":"LFA\/ fiscal note sent to sponsor in Senate 2nd Reading Calendar","chamber":"S","chamber_id":94,"importance":0},{"date":"2022-02-01","action":"Senate\/ to Printing with fiscal note in Senate 2nd Reading Calendar","chamber":"S","chamber_id":94,"importance":0},{"date":"2022-02-03","action":"Senate\/ 2nd reading in Senate 2nd Reading Calendar","chamber":"S","chamber_id":94,"importance":0},{"date":"2022-02-03","action":"Senate\/ substituted from # 1 to # 2 in Senate 2nd Reading Calendar","chamber":"S","chamber_id":94,"importance":0},{"date":"2022-02-03","action":"Senate\/ passed 2nd reading in Senate 3rd Reading Calendar","chamber":"S","chamber_id":94,"importance":0},{"date":"2022-02-04","action":"Senate\/ 3rd reading in Senate 3rd Reading Calendar","chamber":"S","chamber_id":94,"importance":0},{"date":"2022-02-04","action":"Senate\/ passed 3rd reading in Clerk of the House","chamber":"H","chamber_id":93,"importance":0},{"date":"2022-02-04","action":"Senate\/ to House in Clerk of the House","chamber":"H","chamber_id":93,"importance":0},{"date":"2022-02-04","action":"House\/ received from Senate in Clerk of the House","chamber":"H","chamber_id":93,"importance":1},{"date":"2022-02-04","action":"House\/ 1st reading (Introduced) in House Rules Committee","chamber":"H","chamber_id":93,"importance":0},{"date":"2022-02-07","action":"House\/ to standing committee in House Judiciary Committee","chamber":"H","chamber_id":93,"importance":1},{"date":"2022-02-16","action":"House Comm - Favorable Recommendation in House Judiciary Committee","chamber":"H","chamber_id":93,"importance":0},{"date":"2022-02-16","action":"House\/ committee report favorable in House Judiciary Committee","chamber":"H","chamber_id":93,"importance":1},{"date":"2022-02-16","action":"House\/ 2nd reading in House 3rd Reading Calendar for Senate bills","chamber":"H","chamber_id":93,"importance":0},{"date":"2022-02-17","action":"House\/ 3rd reading in House 3rd Reading Calendar for Senate bills","chamber":"H","chamber_id":93,"importance":0},{"date":"2022-02-17","action":"House\/ passed 3rd reading in House Speaker","chamber":"H","chamber_id":93,"importance":0},{"date":"2022-02-17","action":"House\/ signed by Speaker\/ returned to Senate in Senate President","chamber":"S","chamber_id":94,"importance":0},{"date":"2022-02-17","action":"House\/ to Senate in Senate President","chamber":"S","chamber_id":94,"importance":0},{"date":"2022-02-17","action":"Senate\/ received from House in Senate President","chamber":"S","chamber_id":94,"importance":0},{"date":"2022-02-17","action":"Senate\/ signed by President\/ sent for enrolling in Legislative Research and General Counsel \/ Enrolling","chamber":"","chamber_id":0,"importance":0},{"date":"2022-02-21","action":"Bill Received from Senate for Enrolling in Legislative Research and General Counsel \/ Enrolling","chamber":"","chamber_id":0,"importance":0},{"date":"2022-02-21","action":"Draft of Enrolled Bill Prepared in Legislative Research and General Counsel \/ Enrolling","chamber":"","chamber_id":0,"importance":0},{"date":"2022-03-11","action":"Enrolled Bill Returned to House or Senate in Senate Secretary","chamber":"S","chamber_id":94,"importance":0},{"date":"2022-03-11","action":"Senate\/ enrolled bill to Printing in Senate Secretary","chamber":"S","chamber_id":94,"importance":1},{"date":"2022-03-15","action":"Senate\/ received enrolled bill from Printing in Senate Secretary","chamber":"S","chamber_id":94,"importance":0},{"date":"2022-03-15","action":"Senate\/ to Governor in Executive Branch - Governor","chamber":"","chamber_id":0,"importance":0},{"date":"2022-03-23","action":"Governor Signed in Lieutenant Governor's office for filing","chamber":"","chamber_id":0,"importance":1}],"sponsors":[{"people_id":13816,"person_hash":"mw9323ln","party_id":"2","state_id":44,"party":"R","role_id":2,"role":"Sen","name":"Todd Weiler","first_name":"Todd","middle_name":"D.","last_name":"Weiler","suffix":"","nickname":"","district":"SD-023","ftm_eid":6648183,"votesmart_id":50569,"opensecrets_id":"","knowwho_pid":390467,"ballotpedia":"Todd_Weiler","sponsor_type_id":1,"sponsor_order":1,"committee_sponsor":0,"committee_id":0,"state_federal":0},{"people_id":22454,"person_hash":"zbr4wnu0","party_id":"2","state_id":44,"party":"R","role_id":1,"role":"Rep","name":"Nelson Abbott","first_name":"Nelson","middle_name":"T.","last_name":"Abbott","suffix":"","nickname":"","district":"HD-060","ftm_eid":49449546,"votesmart_id":192472,"opensecrets_id":"","knowwho_pid":736260,"ballotpedia":"Nelson_Abbott","sponsor_type_id":3,"sponsor_order":2,"committee_sponsor":0,"committee_id":0,"state_federal":0}],"sasts":[],"subjects":[{"subject_id":11880,"subject_name":"Judicial Administration"},{"subject_id":332528,"subject_name":"Judicial Operations"},{"subject_id":11868,"subject_name":"Courts"},{"subject_id":334142,"subject_name":"Judges"}],"texts":[{"doc_id":2479314,"date":"2022-01-14","type":"Introduced","type_id":1,"mime":"application\/pdf","mime_id":2,"url":"https:\/\/legiscan.com\/UT\/text\/SB0098\/id\/2479314","state_link":"https:\/\/le.utah.gov\/~2022\/bills\/sbillint\/SB0098.pdf","text_size":106947,"text_hash":"01d168c8e4e723fbf1dd32b74cc12a2a"},{"doc_id":2490813,"date":"2022-01-25","type":"Introduced","type_id":1,"mime":"application\/pdf","mime_id":2,"url":"https:\/\/legiscan.com\/UT\/text\/SB0098\/id\/2490813","state_link":"https:\/\/le.utah.gov\/~2022\/bills\/sbillint\/SB0098S01.pdf","text_size":134428,"text_hash":"2c296baacbb1cd5134584bb5a7ed42a5"},{"doc_id":2505500,"date":"2022-02-03","type":"Introduced","type_id":1,"mime":"application\/pdf","mime_id":2,"url":"https:\/\/legiscan.com\/UT\/text\/SB0098\/id\/2505500","state_link":"https:\/\/le.utah.gov\/~2022\/bills\/sbillint\/SB0098S02.pdf","text_size":138329,"text_hash":"4ca046e3ba6a95eade1a5f0a522a78c3"},{"doc_id":2547193,"date":"2022-03-11","type":"Enrolled","type_id":5,"mime":"application\/pdf","mime_id":2,"url":"https:\/\/legiscan.com\/UT\/text\/SB0098\/id\/2547193","state_link":"https:\/\/le.utah.gov\/~2022\/bills\/sbillenr\/SB0098.pdf","text_size":126756,"text_hash":"5c340f6ba8df48518846840befd21a39"}],"votes":[{"roll_call_id":1127630,"date":"2022-01-25","desc":"Senate Comm - Substitute Recommendation from # 0 to # 1","yea":5,"nay":0,"nv":0,"absent":2,"total":7,"passed":1,"chamber":"S","chamber_id":94,"url":"https:\/\/legiscan.com\/UT\/rollcall\/SB0098\/id\/1127630","state_link":"https:\/\/le.utah.gov\/mtgvotes.jsp?voteid=22079"},{"roll_call_id":1127631,"date":"2022-01-25","desc":"Senate Comm - Favorable Recommendation","yea":4,"nay":0,"nv":0,"absent":3,"total":7,"passed":1,"chamber":"S","chamber_id":94,"url":"https:\/\/legiscan.com\/UT\/rollcall\/SB0098\/id\/1127631","state_link":"https:\/\/le.utah.gov\/mtgvotes.jsp?voteid=22083"},{"roll_call_id":1134952,"date":"2022-02-03","desc":"Senate\/ passed 2nd reading","yea":23,"nay":0,"nv":0,"absent":6,"total":29,"passed":1,"chamber":"S","chamber_id":94,"url":"https:\/\/legiscan.com\/UT\/rollcall\/SB0098\/id\/1134952","state_link":"https:\/\/le.utah.gov\/DynaBill\/svotes.jsp?sessionid=2022GS&voteid=309&house=S"},{"roll_call_id":1135266,"date":"2022-02-04","desc":"Senate\/ passed 3rd reading","yea":25,"nay":0,"nv":0,"absent":4,"total":29,"passed":1,"chamber":"S","chamber_id":94,"url":"https:\/\/legiscan.com\/UT\/rollcall\/SB0098\/id\/1135266","state_link":"https:\/\/le.utah.gov\/DynaBill\/svotes.jsp?sessionid=2022GS&voteid=339&house=S"},{"roll_call_id":1146121,"date":"2022-02-16","desc":"House Comm - Favorable Recommendation","yea":9,"nay":0,"nv":0,"absent":3,"total":12,"passed":1,"chamber":"H","chamber_id":93,"url":"https:\/\/legiscan.com\/UT\/rollcall\/SB0098\/id\/1146121","state_link":"https:\/\/le.utah.gov\/mtgvotes.jsp?voteid=23414"},{"roll_call_id":1147651,"date":"2022-02-17","desc":"House\/ passed 3rd reading","yea":70,"nay":0,"nv":0,"absent":5,"total":75,"passed":1,"chamber":"H","chamber_id":93,"url":"https:\/\/legiscan.com\/UT\/rollcall\/SB0098\/id\/1147651","state_link":"https:\/\/le.utah.gov\/DynaBill\/svotes.jsp?sessionid=2022GS&voteid=572&house=H"}],"amendments":[],"supplements":[{"supplement_id":224851,"date":"2022-01-19","type":"Fiscal Note","type_id":1,"title":"Fiscal Note","description":"Fiscal Note SB0098","mime":"application\/pdf","mime_id":2,"url":"https:\/\/legiscan.com\/UT\/supplement\/SB0098\/id\/224851","state_link":"https:\/\/le.utah.gov\/lfa\/fnotes\/2022\/SB0098.fn.pdf","supplement_size":1391509,"supplement_hash":"fb96975034730c3197a35f2f5e1acd4a"},{"supplement_id":228007,"date":"2022-01-25","type":"Analysis","type_id":2,"title":"Analysis","description":"SB0098S01 Compared With SB0098","mime":"application\/pdf","mime_id":2,"url":"https:\/\/legiscan.com\/UT\/supplement\/SB0098\/id\/228007","state_link":"https:\/\/le.utah.gov\/~2022\/bills\/sbillint\/SB0098S01_ComparedWith_SB0098.pdf","supplement_size":152745,"supplement_hash":"a4c815af1fa56e1169b2a457549332f8"},{"supplement_id":230302,"date":"2022-01-28","type":"Fiscal Note","type_id":1,"title":"Fiscal Note","description":"Fiscal Note SB0098S01","mime":"application\/pdf","mime_id":2,"url":"https:\/\/legiscan.com\/UT\/supplement\/SB0098\/id\/230302","state_link":"https:\/\/le.utah.gov\/lfa\/fnotes\/2022\/SB0098S01.fn.pdf","supplement_size":1391920,"supplement_hash":"ef47236c5c36f7189137dd0394e8f595"},{"supplement_id":230796,"date":"2022-01-28","type":"Analysis","type_id":2,"title":"Analysis","description":"SB0098S02 Compared With SB0098S01","mime":"application\/pdf","mime_id":2,"url":"https:\/\/legiscan.com\/UT\/supplement\/SB0098\/id\/230796","state_link":"https:\/\/le.utah.gov\/~2022\/bills\/sbillint\/SB0098S02_ComparedWith_SB0098S01.pdf","supplement_size":154096,"supplement_hash":"77a443207320d3a2ae9b0e28dd13c8c1"},{"supplement_id":232332,"date":"2022-02-01","type":"Fiscal Note","type_id":1,"title":"Fiscal Note","description":"Fiscal Note SB0098S02","mime":"application\/pdf","mime_id":2,"url":"https:\/\/legiscan.com\/UT\/supplement\/SB0098\/id\/232332","state_link":"https:\/\/le.utah.gov\/lfa\/fnotes\/2022\/SB0098S02.fn.pdf","supplement_size":1391923,"supplement_hash":"098957010f4140fe27c1cf893d0657ad"}],"calendar":[{"type_id":1,"type":"Hearing","date":"2022-01-25","time":"14:00","location":"","description":"Senate Judiciary, Law Enforcement, and Criminal Justice Hearing"},{"type_id":1,"type":"Hearing","date":"2022-02-16","time":"08:00","location":"","description":"House Judiciary Hearing"}]}}