{"bill":{"bill_id":1548365,"change_hash":"d5d1d60967dc475c502b2b0f71fa977a","session_id":1831,"session":{"session_id":1831,"state_id":44,"year_start":2022,"year_end":2022,"prefile":0,"sine_die":1,"prior":0,"special":0,"session_tag":"Regular Session","session_title":"2022 Regular Session","session_name":"2022 General Session"},"url":"https:\/\/legiscan.com\/UT\/bill\/SCR005\/2022","state_link":"https:\/\/le.utah.gov\/~2022\/bills\/static\/SCR005.html","completed":1,"status":4,"status_date":"2022-03-03","progress":[{"date":"2022-01-18","event":1},{"date":"2022-01-18","event":9},{"date":"2022-01-20","event":10},{"date":"2022-02-16","event":2},{"date":"2022-02-17","event":9},{"date":"2022-02-23","event":10},{"date":"2022-02-28","event":3},{"date":"2022-03-03","event":4}],"state":"UT","state_id":44,"bill_number":"SCR005","bill_type":"CR","bill_type_id":"3","body":"S","body_id":94,"current_body":"S","current_body_id":94,"title":"Concurrent Resolution Honoring 125th Anniversary of the National Parent Teacher Association","description":"Concurrent Resolution Honoring 125th Anniversary of the National Parent Teacher Association","pending_committee_id":0,"committee":[],"referrals":[{"date":"2022-01-18","committee_id":2128,"chamber":"S","chamber_id":94,"name":"Rules"},{"date":"2022-01-18","committee_id":2120,"chamber":"S","chamber_id":94,"name":"Education"},{"date":"2022-02-16","committee_id":2116,"chamber":"H","chamber_id":93,"name":"Rules"},{"date":"2022-02-17","committee_id":2105,"chamber":"H","chamber_id":93,"name":"Education"}],"history":[{"date":"2022-01-06","action":"Bill Numbered but not Distributed in Legislative Research and General Counsel","chamber":"","chamber_id":0,"importance":0},{"date":"2022-01-07","action":"Numbered Bill Publicly Distributed in Legislative Research and General Counsel","chamber":"","chamber_id":0,"importance":0},{"date":"2022-01-07","action":"LFA\/ bill sent to agencies for fiscal input in Legislative Research and General Counsel","chamber":"","chamber_id":0,"importance":0},{"date":"2022-01-10","action":"LFA\/ fiscal note publicly available in Legislative Research and General Counsel","chamber":"","chamber_id":0,"importance":0},{"date":"2022-01-12","action":"Senate\/ received bill from Legislative Printing in Waiting for Introduction in the Senate","chamber":"S","chamber_id":94,"importance":0},{"date":"2022-01-18","action":"Senate\/ 1st reading (Introduced) in Senate Rules Committee","chamber":"S","chamber_id":94,"importance":1},{"date":"2022-01-18","action":"Senate\/ to standing committee in Senate Education Committee","chamber":"S","chamber_id":94,"importance":1},{"date":"2022-01-19","action":"Senate Comm - Amendment Recommendation # 1 in Senate Education Committee","chamber":"S","chamber_id":94,"importance":0},{"date":"2022-01-19","action":"Senate Comm - Favorable Recommendation in Senate Education Committee","chamber":"S","chamber_id":94,"importance":0},{"date":"2022-01-20","action":"Senate\/ comm rpt\/ amended in Senate Education Committee","chamber":"S","chamber_id":94,"importance":1},{"date":"2022-01-20","action":"Senate\/ placed on 2nd Reading Calendar in Senate 2nd Reading Calendar","chamber":"S","chamber_id":94,"importance":0},{"date":"2022-01-24","action":"Senate\/ placed on Time Certain Calendar in Senate Special Orders Calendar","chamber":"S","chamber_id":94,"importance":0},{"date":"2022-02-16","action":"Senate\/ 2nd & 3rd readings\/ suspension in Clerk of the House","chamber":"H","chamber_id":93,"importance":0},{"date":"2022-02-16","action":"Senate\/ passed 2nd & 3rd readings\/ suspension in Clerk of the House","chamber":"H","chamber_id":93,"importance":0},{"date":"2022-02-16","action":"Senate\/ to House in Clerk of the House","chamber":"H","chamber_id":93,"importance":0},{"date":"2022-02-16","action":"House\/ received from Senate in Clerk of the House","chamber":"H","chamber_id":93,"importance":1},{"date":"2022-02-16","action":"House\/ 1st reading (Introduced) in House Rules Committee","chamber":"H","chamber_id":93,"importance":0},{"date":"2022-02-17","action":"House\/ to standing committee in House Education Committee","chamber":"H","chamber_id":93,"importance":1},{"date":"2022-02-22","action":"House Comm - Favorable Recommendation in House Education Committee","chamber":"H","chamber_id":93,"importance":0},{"date":"2022-02-23","action":"House\/ committee report favorable in House Education Committee","chamber":"H","chamber_id":93,"importance":1},{"date":"2022-02-23","action":"House\/ 2nd reading in House 3rd Reading Calendar for Senate bills","chamber":"H","chamber_id":93,"importance":0},{"date":"2022-02-23","action":"House\/ placed on Time Certain Calendar in House Special Orders Calendar","chamber":"H","chamber_id":93,"importance":0},{"date":"2022-02-25","action":"House\/ 3rd reading in House Special Orders Calendar","chamber":"H","chamber_id":93,"importance":0},{"date":"2022-02-25","action":"House\/ passed 3rd reading in House Speaker","chamber":"H","chamber_id":93,"importance":0},{"date":"2022-02-25","action":"House\/ signed by Speaker\/ returned to Senate in Senate President","chamber":"S","chamber_id":94,"importance":0},{"date":"2022-02-25","action":"House\/ to Senate in Senate President","chamber":"S","chamber_id":94,"importance":0},{"date":"2022-02-25","action":"Senate\/ received from House in Senate President","chamber":"S","chamber_id":94,"importance":0},{"date":"2022-02-25","action":"Senate\/ signed by President\/ sent for enrolling in Legislative Research and General Counsel \/ Enrolling","chamber":"","chamber_id":0,"importance":0},{"date":"2022-02-28","action":"Bill Received from Senate for Enrolling in Legislative Research and General Counsel \/ Enrolling","chamber":"","chamber_id":0,"importance":0},{"date":"2022-02-28","action":"Draft of Enrolled Bill Prepared in Legislative Research and General Counsel \/ Enrolling","chamber":"","chamber_id":0,"importance":0},{"date":"2022-02-28","action":"Enrolled Bill Returned to House or Senate in Senate Secretary","chamber":"S","chamber_id":94,"importance":0},{"date":"2022-02-28","action":"Senate\/ enrolled bill to Printing in Senate Secretary","chamber":"S","chamber_id":94,"importance":1},{"date":"2022-03-03","action":"Senate\/ received enrolled bill from Printing in Senate Secretary","chamber":"S","chamber_id":94,"importance":0},{"date":"2022-03-03","action":"Senate\/ to Governor in Executive Branch - Governor","chamber":"","chamber_id":0,"importance":0},{"date":"2022-03-03","action":"Governor Signed in Lieutenant Governor's office for filing","chamber":"","chamber_id":0,"importance":1}],"sponsors":[{"people_id":17396,"person_hash":"jfea72ig","party_id":"2","state_id":44,"party":"R","role_id":2,"role":"Sen","name":"Ann Millner","first_name":"Ann","middle_name":"","last_name":"Millner","suffix":"","nickname":"","district":"SD-018","ftm_eid":24352067,"votesmart_id":151613,"opensecrets_id":"","knowwho_pid":492263,"ballotpedia":"Ann_Millner","sponsor_type_id":1,"sponsor_order":1,"committee_sponsor":0,"committee_id":0,"state_federal":0},{"people_id":13832,"person_hash":"9rdwv8kh","party_id":"2","state_id":44,"party":"R","role_id":1,"role":"Rep","name":"V. Lowry Snow","first_name":"V. Lowry","middle_name":"","last_name":"Snow","suffix":"","nickname":"","district":"HD-074","ftm_eid":13007284,"votesmart_id":135501,"opensecrets_id":"","knowwho_pid":389062,"ballotpedia":"Lowry_Snow","sponsor_type_id":3,"sponsor_order":2,"committee_sponsor":0,"committee_id":0,"state_federal":0}],"sasts":[],"subjects":[{"subject_id":11987,"subject_name":"Resolutions"},{"subject_id":11846,"subject_name":"Education"},{"subject_id":332526,"subject_name":"K-12 Education"},{"subject_id":332524,"subject_name":"Legislative Operations"}],"texts":[{"doc_id":2467581,"date":"2022-01-07","type":"Introduced","type_id":1,"mime":"application\/pdf","mime_id":2,"url":"https:\/\/legiscan.com\/UT\/text\/SCR005\/id\/2467581","state_link":"https:\/\/le.utah.gov\/~2022\/bills\/sbillint\/SCR005.pdf","text_size":73052,"text_hash":"620532bf3e123affb951ede0e3136483"},{"doc_id":2484820,"date":"2022-01-20","type":"Amended","type_id":3,"mime":"application\/pdf","mime_id":2,"url":"https:\/\/legiscan.com\/UT\/text\/SCR005\/id\/2484820","state_link":"https:\/\/le.utah.gov\/~2022\/bills\/sbillamd\/SCR005.pdf","text_size":81688,"text_hash":"99e9df918263603a172db6d3f9f0e0ae"},{"doc_id":2530651,"date":"2022-02-28","type":"Enrolled","type_id":5,"mime":"application\/pdf","mime_id":2,"url":"https:\/\/legiscan.com\/UT\/text\/SCR005\/id\/2530651","state_link":"https:\/\/le.utah.gov\/~2022\/bills\/sbillenr\/SCR005.pdf","text_size":60993,"text_hash":"b497a0ab92669483134497739da13ca7"}],"votes":[{"roll_call_id":1125790,"date":"2022-01-19","desc":"Senate Comm - Amendment Recommendation # 1","yea":6,"nay":0,"nv":0,"absent":1,"total":7,"passed":1,"chamber":"S","chamber_id":94,"url":"https:\/\/legiscan.com\/UT\/rollcall\/SCR005\/id\/1125790","state_link":"https:\/\/le.utah.gov\/mtgvotes.jsp?voteid=21840"},{"roll_call_id":1125791,"date":"2022-01-19","desc":"Senate Comm - Favorable Recommendation","yea":6,"nay":0,"nv":0,"absent":1,"total":7,"passed":1,"chamber":"S","chamber_id":94,"url":"https:\/\/legiscan.com\/UT\/rollcall\/SCR005\/id\/1125791","state_link":"https:\/\/le.utah.gov\/mtgvotes.jsp?voteid=21843"},{"roll_call_id":1146816,"date":"2022-02-16","desc":"Senate\/ 2nd & 3rd readings\/ suspension","yea":25,"nay":0,"nv":0,"absent":4,"total":29,"passed":1,"chamber":"S","chamber_id":94,"url":"https:\/\/legiscan.com\/UT\/rollcall\/SCR005\/id\/1146816","state_link":"https:\/\/le.utah.gov\/DynaBill\/svotes.jsp?sessionid=2022GS&voteid=693&house=S"},{"roll_call_id":1146817,"date":"2022-02-16","desc":"Senate\/ passed 2nd & 3rd readings\/ suspension","yea":25,"nay":0,"nv":0,"absent":4,"total":29,"passed":1,"chamber":"S","chamber_id":94,"url":"https:\/\/legiscan.com\/UT\/rollcall\/SCR005\/id\/1146817","state_link":"https:\/\/le.utah.gov\/DynaBill\/svotes.jsp?sessionid=2022GS&voteid=693&house=S"},{"roll_call_id":1151179,"date":"2022-02-22","desc":"House Comm - Favorable Recommendation","yea":7,"nay":0,"nv":0,"absent":8,"total":15,"passed":1,"chamber":"H","chamber_id":93,"url":"https:\/\/legiscan.com\/UT\/rollcall\/SCR005\/id\/1151179","state_link":"https:\/\/le.utah.gov\/mtgvotes.jsp?voteid=23716"},{"roll_call_id":1155014,"date":"2022-02-25","desc":"House\/ passed 3rd reading","yea":70,"nay":0,"nv":0,"absent":5,"total":75,"passed":1,"chamber":"H","chamber_id":93,"url":"https:\/\/legiscan.com\/UT\/rollcall\/SCR005\/id\/1155014","state_link":"https:\/\/le.utah.gov\/DynaBill\/svotes.jsp?sessionid=2022GS&voteid=832&house=H"}],"amendments":[{"amendment_id":123206,"adopted":1,"chamber":"S","chamber_id":94,"date":"2022-01-19","title":"Senate Committee Amendment 1","description":"Senate Committee Amendment 1","mime":"application\/pdf","mime_id":2,"url":"https:\/\/legiscan.com\/UT\/amendment\/SCR005\/id\/123206","state_link":"https:\/\/le.utah.gov\/~2022\/pamend\/scr005.sca.01.pdf","amendment_size":70103,"amendment_hash":"1e44d45af8f2d91ea89151fed1acc0bc"}],"supplements":[{"supplement_id":220855,"date":"2022-01-08","type":"Misc","type_id":7,"title":"Misc","description":"Agency Perf Note SCR005","mime":"application\/pdf","mime_id":2,"url":"https:\/\/legiscan.com\/UT\/supplement\/SCR005\/id\/220855","state_link":"https:\/\/le.utah.gov\/lfa\/fnotes\/2022\/SCR005.pna.pdf","supplement_size":1388552,"supplement_hash":"b10e2d9c0c069e57e1e07085a09a8df2"},{"supplement_id":220964,"date":"2022-01-10","type":"Fiscal Note","type_id":1,"title":"Fiscal Note","description":"Fiscal Note SCR005","mime":"application\/pdf","mime_id":2,"url":"https:\/\/legiscan.com\/UT\/supplement\/SCR005\/id\/220964","state_link":"https:\/\/le.utah.gov\/lfa\/fnotes\/2022\/SCR005.fn.pdf","supplement_size":1390810,"supplement_hash":"b8e34127605cb5da3801ef553390f361"}],"calendar":[{"type_id":1,"type":"Hearing","date":"2022-01-19","time":"14:00","location":"","description":"Senate Education Hearing"},{"type_id":1,"type":"Hearing","date":"2022-02-22","time":"16:00","location":"","description":"House Education Hearing"}]}}